PyAsyncHelper3/__init__.py
PyAsyncHelper3/global_v.py
PyAsyncHelper3/core/AsyncManager.py
PyAsyncHelper3/core/Gear.py
PyAsyncHelper3/core/Global.py
PyAsyncHelper3/core/Logging.py
PyAsyncHelper3/core/Router.py
PyAsyncHelper3/core/WorkerBase.py
PyAsyncHelper3/core/__init__.py
PyAsyncHelper3/model/__init__.py
PyAsyncHelper3/worker/MQTTWorker.py
PyAsyncHelper3/worker/__init__.py
core/AsyncManager.py
core/Gear.py
core/Global.py
core/Logging.py
core/Router.py
core/WorkerBase.py
core/__init__.py
model/__init__.py
worker/MQTTWorker.py
worker/__init__.py
PyAsyncHelper3-0.0.2.dist-info/METADATA
PyAsyncHelper3-0.0.2.dist-info/WHEEL
PyAsyncHelper3-0.0.2.dist-info/top_level.txt
PyAsyncHelper3-0.0.2.dist-info/RECORD
