Metadata-Version: 2.1
Name: PyAsyncHelper3
Version: 0.0.2
Summary: dispatcher base on async
Home-page: http://gitee.com/shellvv/PyAsyncHelper3
Author: shellvv
Author-email: shellvv@yeah.com
License: UNKNOWN
Platform: UNKNOWN
Classifier: Programming Language :: Python :: 3
Classifier: License :: OSI Approved :: MIT License
Classifier: Operating System :: OS Independent
Requires-Dist: pyhelper3
